cto_ai/__init__.py
cto_ai/daemon_request.py
cto_ai/prompt.py
cto_ai/sdk.py
cto_ai/ux.py
cto_ai-2.3.3.dist-info/LICENSE
cto_ai-2.3.3.dist-info/METADATA
cto_ai-2.3.3.dist-info/WHEEL
cto_ai-2.3.3.dist-info/top_level.txt
cto_ai-2.3.3.dist-info/RECORD
