Metadata-Version: 2.1
Name: cto-ai
Version: 2.3.3
Summary: SDK for The Ops Platform
Home-page: https://github.com/cto-ai/sdk-python
Author: CTO.ai
Author-email: devops@cto.ai
License: UNKNOWN
Platform: UNKNOWN
Classifier: Programming Language :: Python :: 3
Classifier: License :: OSI Approved :: MIT License
Classifier: Operating System :: POSIX :: Linux
Requires-Python: >=3.6
Requires-Dist: requests (>=2.22)
